pwh_pyramid_session/__init__.py
pwh_pyramid_session-1.0.0.dist-info/WHEEL
pwh_pyramid_session-1.0.0.dist-info/METADATA
pwh_pyramid_session-1.0.0.dist-info/RECORD
