Metadata-Version: 2.1
Name: pwh-pyramid-session
Version: 1.0.0
Summary: Session helpers for Pyramid
License: MIT
Author: Mark Hall
Author-email: mark.hall@work.room3b.eu
Requires-Python: >=3.7,<4.0
Classifier: License :: OSI Approved :: MIT License
Classifier: Programming Language :: Python :: 3
Classifier: Programming Language :: Python :: 3.7
Classifier: Programming Language :: Python :: 3.8
Requires-Dist: decorator (>=4.4.2,<5.0.0)
Requires-Dist: pwh_pyramid_routes (>=1.0.0,<2.0.0)
Requires-Dist: pyramid_nacl_session (>=0.3,<0.4)
Requires-Dist: sqlalchemy (>=1.3.16,<2.0.0)
